<?xml version="1.0" encoding="utf-8"?>
<parse name="AccountServerMicroTrans2DefRequiredNotPurchase">
  <table>
    <column name="AccountServerMicroTrans2DefRequiredNotPurchase" type="IGNORE">
      <flags>
        <flag>PARSETABLE_INFO</flag>
      </flags>
    </column>
    <column name="{" type="START" />
    <column name="Name" type="STRING">
      <offset>0</offset>
      <flags>
        <flag>POOL_STRING</flag>
        <flag>CASE_SENSITIVE</flag>
      </flags>
    </column>
    <column name="Value" type="INT">
      <offset>8</offset>
    </column>
    <column name="Shardscoping" type="EMBEDDEDSTRUCT">
      <offset>16</offset>
      <subtable external="AccountServerMicroTrans2ShardScoping" />
    </column>
    <column name="}" type="END" />
  </table>
</parse>