<?xml version="1.0" encoding="utf-8"?>
<parse name="DaboResultIndex">
  <table>
    <column name="DaboResultIndex" type="IGNORE">
      <flags>
        <flag>PARSETABLE_INFO</flag>
      </flags>
    </column>
    <column name="{" type="START" />
    <column name="Wheelindex" type="INT">
      <offset>0</offset>
    </column>
    <column name="Payoutpercent" type="F32">
      <offset>4</offset>
    </column>
    <column name="Matchedcolor" type="INT">
      <offset>8</offset>
    </column>
    <column name="Matchedshape" type="INT">
      <offset>12</offset>
    </column>
    <column name="Matchedcount" type="INT">
      <offset>16</offset>
    </column>
    <column name="Quarks" type="INT">
      <offset>20</offset>
    </column>
    <column name="Ds9s" type="INT">
      <offset>24</offset>
    </column>
    <column name="Wilds" type="INT">
      <offset>28</offset>
    </column>
    <column name="Dabo" type="U8">
      <offset>32</offset>
      <format>INT_WAS_BOOL</format>
    </column>
    <column name="Hasresults" type="U8">
      <offset>33</offset>
      <format>INT_WAS_BOOL</format>
    </column>
    <column name="Betinfo" type="STRUCT">
      <offset>40</offset>
      <subtable external="DaboSpectatorBetInfo" />
    </column>
    <column name="}" type="END" />
  </table>
</parse>