<?xml version="1.0" encoding="utf-8"?>
<parse name="GenesisZoneMission">
  <table>
    <column name="GenesisZoneMission" type="IGNORE">
      <flags>
        <flag>PARSETABLE_INFO</flag>
      </flags>
    </column>
    <column name="{" type="START" />
    <column name="Desc" type="IGNORE">
      <flags>
        <flag>FLATEMBED</flag>
      </flags>
      <format_strings>
        <format_string name="EMBEDDED_STRUCT">GenesisMissionZoneDescription</format_string>
      </format_strings>
    </column>
    <column name="Name" type="STRING">
      <offset>0</offset>
    </column>
    <column name="DisplayName" type="STRING">
      <offset>8</offset>
    </column>
    <column name="Uistring" type="STRING">
      <offset>16</offset>
    </column>
    <column name="Shorttext" type="STRING">
      <offset>16</offset>
      <flags>
        <flag>REDUNDANTNAME</flag>
      </flags>
      <redundant_name>Uistring</redundant_name>
    </column>
    <column name="Descriptiontext" type="STRING">
      <offset>24</offset>
    </column>
    <column name="Summary" type="STRING">
      <offset>32</offset>
    </column>
    <column name="Returntext" type="STRING">
      <offset>40</offset>
    </column>
    <column name="Category" type="REFERENCE">
      <offset>48</offset>
      <dictionary_name>MissionCategory</dictionary_name>
    </column>
    <column name="Playtype" type="INT">
      <offset>56</offset>
      <static_define_list external="MissionPlayType" />
    </column>
    <column name="Authorsource" type="INT">
      <offset>60</offset>
      <static_define_list external="ContentAuthorSource" />
    </column>
    <column name="Leveldef" type="IGNORE">
      <flags>
        <flag>FLATEMBED</flag>
      </flags>
      <format_strings>
        <format_string name="EMBEDDED_STRUCT">MissionLevelDef</format_string>
      </format_strings>
    </column>
    <column name="Leveltype" type="INT">
      <offset>64</offset>
      <static_define_list external="MissionLevelType" />
    </column>
    <column name="Useplayerlevel" type="INT">
      <offset>64</offset>
      <flags>
        <flag>REDUNDANTNAME</flag>
      </flags>
      <redundant_name>Leveltype</redundant_name>
      <static_define_list external="MissionLevelType" />
    </column>
    <column name="Level" type="INT">
      <offset>68</offset>
      <default>1</default>
    </column>
    <column name="Level:" type="INT">
      <offset>68</offset>
      <flags>
        <flag>REDUNDANTNAME</flag>
      </flags>
      <redundant_name>Level</redundant_name>
      <default>1</default>
    </column>
    <column name="Mapvariableforlevel" type="STRING">
      <offset>72</offset>
    </column>
    <column name="Levelclamp" type="OPTIONALSTRUCT">
      <offset>80</offset>
      <subtable external="MissionLevelClamp" />
    </column>
    <column name="EventName" type="STRING">
      <offset>88</offset>
      <flags>
        <flag>POOL_STRING</flag>
      </flags>
    </column>
    <column name="Minleveloverride" type="INT">
      <offset>96</offset>
    </column>
    <column name="Shareable" type="INT">
      <offset>104</offset>
      <static_define_list external="MissionShareableType" />
    </column>
    <column name="Reward" type="REFERENCE">
      <offset>112</offset>
      <dictionary_name>RewardTable</dictionary_name>
    </column>
    <column name="Rewardscale" type="F32">
      <offset>120</offset>
    </column>
    <column name="Grant" type="EMBEDDEDSTRUCT">
      <offset>128</offset>
      <subtable external="GenesisMissionGrantDescription" />
    </column>
    <column name="Generationtype" type="INT">
      <offset>200</offset>
      <static_define_list external="GenesisMissionGenerationType" />
    </column>
    <column name="Isopenmission" type="INT">
      <offset>200</offset>
      <flags>
        <flag>REDUNDANTNAME</flag>
      </flags>
      <redundant_name>Generationtype</redundant_name>
      <static_define_list external="GenesisMissionGenerationType" />
    </column>
    <column name="Openmission" type="OPTIONALSTRUCT">
      <offset>208</offset>
      <subtable external="GenesisMissionOpenMissionDescription" />
    </column>
    <column name="Start" type="EMBEDDEDSTRUCT">
      <offset>216</offset>
      <subtable external="GenesisMissionStartDescription" />
    </column>
    <column name="Prompt" type="STRUCT">
      <offset>520</offset>
      <subtable external="GenesisMissionPrompt" />
    </column>
    <column name="FSMs" type="STRUCT">
      <offset>528</offset>
      <subtable external="GenesisFSM" />
    </column>
    <column name="Portal" type="STRUCT">
      <offset>536</offset>
      <subtable external="GenesisMissionPortal" />
    </column>
    <column name="Droprewardtable" type="REFERENCE">
      <offset>544</offset>
      <dictionary_name>RewardTable</dictionary_name>
    </column>
    <column name="Dropchallengename" type="STRINGARRAY">
      <offset>552</offset>
    </column>
    <column name="Objective" type="STRUCT">
      <offset>560</offset>
      <subtable external="GenesisMissionObjective" />
    </column>
    <column name="Challenge" type="STRUCT">
      <offset>568</offset>
      <subtable external="GenesisMissionZoneChallenge" />
    </column>
    <column name="Roomrequirement" type="IGNORE">
      <flags>
        <flag>IGNORE_STRUCT</flag>
      </flags>
    </column>
    <column name="}" type="END" />
  </table>
</parse>