<?xml version="1.0" encoding="utf-8"?>
<parse name="PlayerMatchDesc">
  <table>
    <column name="PlayerMatchDesc" type="IGNORE">
      <flags>
        <flag>PARSETABLE_INFO</flag>
      </flags>
    </column>
    <column name="{" type="START" />
    <column name="MatchDefName" type="STRING">
      <offset>0</offset>
      <flags>
        <flag>POOL_STRING</flag>
        <flag>KEY</flag>
      </flags>
    </column>
    <column name="Collection" type="STRING">
      <offset>8</offset>
      <flags>
        <flag>POOL_STRING</flag>
      </flags>
    </column>
    <column name="Location" type="STRING">
      <offset>16</offset>
      <flags>
        <flag>POOL_STRING</flag>
      </flags>
    </column>
    <column name="Translatedmatchdefdisplayname" type="STRING">
      <offset>24</offset>
      <flags>
        <flag>ESTRING</flag>
      </flags>
    </column>
    <column name="Translatedmatchdefdescription" type="STRING">
      <offset>32</offset>
      <flags>
        <flag>ESTRING</flag>
      </flags>
    </column>
    <column name="Translatedmatchdefdescriptionprivate" type="STRING">
      <offset>40</offset>
      <flags>
        <flag>ESTRING</flag>
      </flags>
    </column>
    <column name="Categorydisplayname" type="STRING">
      <offset>48</offset>
      <flags>
        <flag>ESTRING</flag>
      </flags>
    </column>
    <column name="Categoryicon" type="STRING">
      <offset>56</offset>
      <flags>
        <flag>POOL_STRING</flag>
      </flags>
    </column>
    <column name="Icon" type="STRING">
      <offset>64</offset>
      <flags>
        <flag>POOL_STRING</flag>
      </flags>
    </column>
    <column name="Cooldowndefname" type="STRING">
      <offset>72</offset>
      <flags>
        <flag>POOL_STRING</flag>
      </flags>
    </column>
    <column name="Category" type="INTARRAY">
      <offset>80</offset>
      <static_define_list external="MatchCategory" />
    </column>
    <column name="Secondarycategory" type="INTARRAY">
      <offset>80</offset>
      <flags>
        <flag>REDUNDANTNAME</flag>
      </flags>
      <redundant_name>Category</redundant_name>
      <static_define_list external="MatchCategory" />
    </column>
    <column name="Pvpgametype" type="INT">
      <offset>88</offset>
      <static_define_list external="PVPGameType" />
    </column>
    <column name="Matchalgotype" type="INT">
      <offset>92</offset>
      <static_define_list external="MatchAlgoType" />
    </column>
    <column name="Hidefrommatchuilists" type="U8">
      <offset>96</offset>
      <format>INT_WAS_BOOL</format>
    </column>
    <column name="Uplayerinvalidreason" type="INT">
      <offset>100</offset>
    </column>
    <column name="Ugroupinvalidreason" type="INT">
      <offset>104</offset>
    </column>
    <column name="Uprivateinvalidreason" type="INT">
      <offset>108</offset>
    </column>
    <column name="Uvolatileinvalidreason" type="INT">
      <offset>112</offset>
    </column>
    <column name="Playerinvalidreasonmessagekey" type="STRING">
      <offset>120</offset>
      <flags>
        <flag>POOL_STRING</flag>
      </flags>
    </column>
    <column name="Expectedgametime" type="INT">
      <offset>128</offset>
    </column>
    <column name="Maxmatchrequestgroupsizepublic" type="INT">
      <offset>132</offset>
    </column>
    <column name="Maxmatchrequestgroupsizeprivate" type="INT">
      <offset>136</offset>
    </column>
    <column name="Groupsizes" type="INTARRAY">
      <offset>144</offset>
    </column>
    <column name="MinLevel" type="INT">
      <offset>152</offset>
    </column>
    <column name="MaxLevel" type="INT">
      <offset>156</offset>
    </column>
    <column name="Sorttiebreak" type="INT">
      <offset>160</offset>
    </column>
    <column name="Compositelevel" type="INT">
      <offset>164</offset>
    </column>
    <column name="Publicrequiredgearrating" type="INT">
      <offset>168</offset>
    </column>
    <column name="Privategearratingdiff" type="INT">
      <offset>172</offset>
    </column>
    <column name="Leaverpenaltyenabled" type="U8">
      <offset>176</offset>
      <format>INT_WAS_BOOL</format>
    </column>
    <column name="Leaverpenaltyduration" type="INT">
      <offset>180</offset>
    </column>
    <column name="CooldownTime" type="INT">
      <offset>184</offset>
    </column>
    <column name="Critterratingdisplay" type="F32">
      <offset>188</offset>
    </column>
    <column name="Hasbeencompleted" type="U8">
      <offset>192</offset>
      <format>INT_WAS_BOOL</format>
    </column>
    <column name="Randomqueuegroupindexes" type="INTARRAY">
      <offset>200</offset>
    </column>
    <column name="Difficulty" type="INT">
      <offset>208</offset>
      <static_define_list external="MatchDifficulty" />
    </column>
    <column name="Reward" type="INTARRAY">
      <offset>216</offset>
      <static_define_list external="MatchReward" />
    </column>
    <column name="Secondaryreward" type="INTARRAY">
      <offset>216</offset>
      <flags>
        <flag>REDUNDANTNAME</flag>
      </flags>
      <redundant_name>Reward</redundant_name>
      <static_define_list external="MatchReward" />
    </column>
    <column name="Set" type="INT">
      <offset>224</offset>
      <static_define_list external="MatchSet" />
    </column>
    <column name="Regionflags" type="INT">
      <offset>228</offset>
      <static_define_list external="ControlSchemeRegionType" />
    </column>
    <column name="Maptypes" type="INTARRAY">
      <offset>232</offset>
      <static_define_list external="ZoneMapType" />
    </column>
    <column name="Privatesetting" type="STRUCT">
      <offset>240</offset>
      <subtable external="PlayerMatchSetting" />
    </column>
    <column name="Requiredgearrating" type="INT">
      <offset>248</offset>
      <flags>
        <flag>CLIENT_ONLY</flag>
      </flags>
    </column>
    <column name="Maxmatchrequestgroupsize" type="INT">
      <offset>252</offset>
      <flags>
        <flag>CLIENT_ONLY</flag>
      </flags>
    </column>
    <column name="Averagewaittime" type="INT">
      <offset>256</offset>
      <flags>
        <flag>CLIENT_ONLY</flag>
      </flags>
    </column>
    <column name="Numplayersinqueue" type="INT">
      <offset>260</offset>
      <flags>
        <flag>CLIENT_ONLY</flag>
      </flags>
    </column>
    <column name="Isinmatch" type="U8">
      <offset>264</offset>
      <flags>
        <flag>CLIENT_ONLY</flag>
      </flags>
      <format>INT_WAS_BOOL</format>
    </column>
    <column name="Isinsetmatch" type="U8">
      <offset>265</offset>
      <flags>
        <flag>CLIENT_ONLY</flag>
      </flags>
      <format>INT_WAS_BOOL</format>
    </column>
    <column name="Iswaitingformap" type="U8">
      <offset>266</offset>
      <flags>
        <flag>CLIENT_ONLY</flag>
      </flags>
      <format>INT_WAS_BOOL</format>
    </column>
    <column name="Iswaitingforsetmap" type="U8">
      <offset>267</offset>
      <flags>
        <flag>CLIENT_ONLY</flag>
      </flags>
      <format>INT_WAS_BOOL</format>
    </column>
    <column name="}" type="END" />
  </table>
</parse>