<?xml version="1.0" encoding="utf-8"?>
<parse name="PowerTreeSteps">
  <table>
    <column name="PowerTreeSteps" type="IGNORE">
      <flags>
        <flag>PARSETABLE_INFO</flag>
      </flags>
    </column>
    <column name="{" type="START" />
    <column name="Steps" type="STRUCT">
      <offset>0</offset>
      <subtable external="PowerTreeStep" />
    </column>
    <column name="Uipowertreemodcount" type="INT">
      <offset>8</offset>
    </column>
    <column name="Respecskillpointspentmin" type="INT">
      <offset>12</offset>
    </column>
    <column name="Updatepointsspent" type="BIT">
      <offset>16</offset>
      <bit_offset>65536</bit_offset>
    </column>
    <column name="Istraining" type="BIT">
      <offset>16</offset>
      <bit_offset>65537</bit_offset>
    </column>
    <column name="Onlylowerpoints" type="BIT">
      <offset>16</offset>
      <bit_offset>65539</bit_offset>
    </column>
    <column name="}" type="END" />
  </table>
</parse>