<?xml version="1.0" encoding="utf-8"?>
<parse name="ProgressionUpdateParams">
  <table>
    <column name="ProgressionUpdateParams" type="IGNORE">
      <flags>
        <flag>PARSETABLE_INFO</flag>
      </flags>
    </column>
    <column name="{" type="START" />
    <column name="Hoverridenode" type="REFERENCE">
      <offset>0</offset>
      <dictionary_name>GameProgressionNodeDef</dictionary_name>
    </column>
    <column name="Overridetime" type="INT">
      <offset>8</offset>
    </column>
    <column name="Destroyteamdata" type="BIT">
      <offset>12</offset>
      <bit_offset>65536</bit_offset>
    </column>
    <column name="Ppchmissionstouncomplete" type="STRINGARRAY">
      <offset>16</offset>
      <flags>
        <flag>POOL_STRING</flag>
      </flags>
    </column>
    <column name="}" type="END" />
  </table>
</parse>