<?xml version="1.0" encoding="utf-8"?>
<parse name="UIGenMovableBoxState">
  <table>
    <column name="UIGenMovableBoxState" type="IGNORE">
      <flags>
        <flag>PARSETABLE_INFO</flag>
      </flags>
    </column>
    <column name="{" type="START" />
    <column name="Type" type="INT">
      <offset>0</offset>
      <flags>
        <flag>OBJECTTYPE</flag>
      </flags>
      <default>14</default>
      <static_define_list external="UIGenType" />
    </column>
    <column name="Original" type="EMBEDDEDSTRUCT">
      <offset>4</offset>
      <subtable external="UIPosition" />
    </column>
    <column name="Override" type="OPTIONALSTRUCT">
      <offset>88</offset>
      <subtable external="UIPosition" />
    </column>
    <column name="Moving" type="U8">
      <offset>96</offset>
      <format>INT_WAS_BOOL</format>
    </column>
    <column name="Resizing" type="INT">
      <offset>100</offset>
      <static_define_list external="UIDirection" />
    </column>
    <column name="Grabbedx" type="INT">
      <offset>104</offset>
    </column>
    <column name="Grabbedy" type="INT">
      <offset>108</offset>
    </column>
    <column name="Chpriority" type="U8">
      <offset>112</offset>
    </column>
    <column name="}" type="END" />
  </table>
</parse>