<?xml version="1.0" encoding="utf-8"?>
<parser name="CharacterPath">
  <table>
    <column name="CharacterPath" type="IGNORE">
      <flags>
        <flag>PARSETABLE_INFO</flag>
      </flags>
    </column>
    <column name="{" type="START" />
    <column name="Name" type="STRING">
      <offset>0</offset>
      <flags>
        <flag>STRUCTPARAM</flag>
        <flag>KEY</flag>
      </flags>
    </column>
    <column name="File" type="CURRENTFILE">
      <offset>8</offset>
      <flags>
        <flag>POOL_STRING</flag>
      </flags>
    </column>
    <column name="DisplayName" type="EMBEDDEDSTRUCT">
      <offset>16</offset>
      <subtable external="DisplayMessage" />
    </column>
    <column name="Header1" type="EMBEDDEDSTRUCT">
      <offset>40</offset>
      <subtable external="DisplayMessage" />
    </column>
    <column name="Header2" type="EMBEDDEDSTRUCT">
      <offset>64</offset>
      <subtable external="DisplayMessage" />
    </column>
    <column name="Header3" type="EMBEDDEDSTRUCT">
      <offset>88</offset>
      <subtable external="DisplayMessage" />
    </column>
    <column name="Description" type="EMBEDDEDSTRUCT">
      <offset>112</offset>
      <subtable external="DisplayMessage" />
    </column>
    <column name="Description1" type="EMBEDDEDSTRUCT">
      <offset>112</offset>
      <flags>
        <flag>REDUNDANTNAME</flag>
      </flags>
      <redundant_name>Description</redundant_name>
      <subtable external="DisplayMessage" />
    </column>
    <column name="Description2" type="EMBEDDEDSTRUCT">
      <offset>136</offset>
      <subtable external="DisplayMessage" />
    </column>
    <column name="Description3" type="EMBEDDEDSTRUCT">
      <offset>160</offset>
      <subtable external="DisplayMessage" />
    </column>
    <column name="Flavortext" type="EMBEDDEDSTRUCT">
      <offset>184</offset>
      <subtable external="DisplayMessage" />
    </column>
    <column name="IconName" type="STRING">
      <offset>208</offset>
      <flags>
        <flag>POOL_STRING</flag>
      </flags>
    </column>
    <column name="Largeimage" type="STRING">
      <offset>216</offset>
      <flags>
        <flag>POOL_STRING</flag>
      </flags>
    </column>
    <column name="ExprRequiresBlock" type="OPTIONALSTRUCT">
      <offset>224</offset>
      <subtable external="Expression" />
    </column>
    <column name="ExprRequires" type="OPTIONALSTRUCT">
      <offset>224</offset>
      <flags>
        <flag>REDUNDANTNAME</flag>
      </flags>
      <redundant_name>ExprRequiresBlock</redundant_name>
      <subtable external="Expression_StructParam" />
    </column>
    <column name="Activityrequired" type="STRING">
      <offset>232</offset>
      <flags>
        <flag>POOL_STRING</flag>
      </flags>
    </column>
    <column name="Powertree" type="REFERENCE">
      <offset>240</offset>
      <dictionary_name>PowerTreeDef</dictionary_name>
    </column>
    <column name="Suggestedpurchase" type="STRUCT">
      <offset>248</offset>
      <subtable external="CharacterPathSuggestedPurchase" />
    </column>
    <column name="Purchase" type="STRUCT">
      <offset>248</offset>
      <flags>
        <flag>REDUNDANTNAME</flag>
      </flags>
      <redundant_name>Suggestedpurchase</redundant_name>
      <subtable external="CharacterPathSuggestedPurchase" />
    </column>
    <column name="Assignedstat" type="STRUCT">
      <offset>256</offset>
      <subtable external="AssignedStats" />
    </column>
    <column name="Grantitem" type="STRUCT">
      <offset>264</offset>
      <subtable external="DefaultItemDef" />
    </column>
    <column name="Requiredclass" type="STRUCT">
      <offset>272</offset>
      <subtable external="CharacterClassRef" />
    </column>
    <column name="Previewitem" type="STRUCT">
      <offset>280</offset>
      <subtable external="ItemDefRef" />
    </column>
    <column name="Hue" type="F32">
      <offset>288</offset>
    </column>
    <column name="Type" type="INT">
      <offset>292</offset>
      <default>-1</default>
      <static_define_list external="CharacterPathType" />
    </column>
    <column name="Role" type="INT">
      <offset>296</offset>
      <static_define_list external="CharacterRole" />
    </column>
    <column name="Gamepermissionvalue" type="STRING">
      <offset>304</offset>
    </column>
    <column name="Gameaccountkey" type="STRING">
      <offset>312</offset>
    </column>
    <column name="Freeretrainitems" type="STRUCT">
      <offset>320</offset>
      <subtable external="DefaultItemDef" />
    </column>
    <column name="Costume" type="STRUCT">
      <offset>328</offset>
      <subtable external="PlayerDefaultCostumeRef" />
    </column>
    <column name="Costumecategory" type="REFERENCE">
      <offset>336</offset>
      <dictionary_name>PCCategory</dictionary_name>
    </column>
    <column name="Gamespecificcharacterpath" type="OPTIONALSTRUCT">
      <offset>344</offset>
      <subtable external="GameSpecificCharacterPath" />
    </column>
    <column name="Combatreactivepowerdef" type="STRING">
      <offset>352</offset>
    </column>
    <column name="Playerpathdevrestricted" type="BIT">
      <offset>360</offset>
      <bit_offset>65536</bit_offset>
    </column>
    <column name="Hideifcantuse" type="BIT">
      <offset>360</offset>
      <bit_offset>65537</bit_offset>
    </column>
    <column name="Disablecharacterbasedinclude" type="BIT">
      <offset>360</offset>
      <bit_offset>65538</bit_offset>
    </column>
    <column name="}" type="END" />
  </table>
</parser>