<?xml version="1.0" encoding="utf-8"?>
<parser name="CutsceneDOF">
  <table>
    <column name="CutsceneDOF" type="IGNORE">
      <flags>
        <flag>PARSETABLE_INFO</flag>
      </flags>
    </column>
    <column name="{" type="START" />
    <column name="Neardist" type="F32">
      <offset>0</offset>
    </column>
    <column name="Nearvalue" type="F32">
      <offset>4</offset>
    </column>
    <column name="Focusdist" type="F32">
      <offset>8</offset>
    </column>
    <column name="Focusvalue" type="F32">
      <offset>12</offset>
    </column>
    <column name="FarDist" type="F32">
      <offset>16</offset>
    </column>
    <column name="Farvalue" type="F32">
      <offset>20</offset>
    </column>
    <column name="Fade_In" type="U8">
      <offset>24</offset>
      <format>INT_WAS_BOOL</format>
    </column>
    <column name="Fade_In_Rate" type="F32">
      <offset>28</offset>
    </column>
    <column name="Fade_Out" type="U8">
      <offset>32</offset>
      <format>INT_WAS_BOOL</format>
    </column>
    <column name="Fade_Out_Rate" type="F32">
      <offset>36</offset>
    </column>
    <column name="Blursize" type="IGNORE" />
    <column name="}" type="END" />
  </table>
</parser>