<?xml version="1.0" encoding="utf-8"?>
<parser name="EmailV3Message">
  <table>
    <column name="EmailV3Message" type="IGNORE">
      <flags>
        <flag>PARSETABLE_INFO</flag>
      </flags>
    </column>
    <column name="{" type="START" />
    <column name="UID" type="INT">
      <offset>0</offset>
      <flags>
        <flag>SUBSCRIBE</flag>
        <flag>KEY</flag>
        <flag>PERSIST</flag>
      </flags>
    </column>
    <column name="Usent" type="INT">
      <offset>4</offset>
      <flags>
        <flag>SUBSCRIBE</flag>
        <flag>PERSIST</flag>
      </flags>
      <format_strings>
        <format_string name="HTML_SECS">1</format_string>
      </format_strings>
    </column>
    <column name="Uexpiretime" type="INT">
      <offset>8</offset>
      <flags>
        <flag>SUBSCRIBE</flag>
        <flag>PERSIST</flag>
      </flags>
      <format_strings>
        <format_string name="HTML_SECS">1</format_string>
      </format_strings>
    </column>
    <column name="Udeletedtime" type="INT">
      <offset>12</offset>
      <flags>
        <flag>PERSIST</flag>
      </flags>
      <format_strings>
        <format_string name="HTML_SECS">1</format_string>
      </format_strings>
    </column>
    <column name="Pchsubject" type="STRING">
      <offset>16</offset>
      <flags>
        <flag>SUBSCRIBE</flag>
        <flag>PERSIST</flag>
      </flags>
    </column>
    <column name="Pchbody" type="STRING">
      <offset>24</offset>
      <flags>
        <flag>SUBSCRIBE</flag>
        <flag>PERSIST</flag>
      </flags>
    </column>
    <column name="Ppitems" type="STRUCT">
      <offset>32</offset>
      <flags>
        <flag>SUBSCRIBE</flag>
        <flag>PERSIST</flag>
        <flag>NO_INDEX</flag>
      </flags>
      <subtable external="Item" />
    </column>
    <column name="Ppclaimeditems" type="STRUCT">
      <offset>40</offset>
      <flags>
        <flag>PERSIST</flag>
        <flag>NO_INDEX</flag>
      </flags>
      <subtable external="EmailV3ClaimedItem" />
    </column>
    <column name="Usenderid" type="INT">
      <offset>48</offset>
      <flags>
        <flag>SUBSCRIBE</flag>
        <flag>PERSIST</flag>
      </flags>
    </column>
    <column name="Pchsenderxuid" type="STRING">
      <offset>56</offset>
      <flags>
        <flag>SUBSCRIBE</flag>
        <flag>PERSIST</flag>
      </flags>
    </column>
    <column name="Pchsendername" type="STRING">
      <offset>64</offset>
      <flags>
        <flag>SUBSCRIBE</flag>
        <flag>PERSIST</flag>
      </flags>
    </column>
    <column name="Pchsenderhandle" type="STRING">
      <offset>72</offset>
      <flags>
        <flag>SUBSCRIBE</flag>
        <flag>PERSIST</flag>
      </flags>
    </column>
    <column name="Typeofemail" type="INT">
      <offset>80</offset>
      <flags>
        <flag>SUBSCRIBE</flag>
        <flag>PERSIST</flag>
      </flags>
      <static_define_list external="EMailV3SenderType" />
    </column>
    <column name="Esendertype" type="INT">
      <offset>80</offset>
      <flags>
        <flag>REDUNDANTNAME</flag>
        <flag>SUBSCRIBE</flag>
        <flag>PERSIST</flag>
      </flags>
      <redundant_name>Typeofemail</redundant_name>
      <static_define_list external="EMailV3SenderType" />
    </column>
    <column name="Econtenttype" type="INT">
      <offset>84</offset>
      <flags>
        <flag>SUBSCRIBE</flag>
        <flag>PERSIST</flag>
      </flags>
      <static_define_list external="EMailV3ContentType" />
    </column>
    <column name="Bread" type="BIT">
      <offset>88</offset>
      <flags>
        <flag>SUBSCRIBE</flag>
        <flag>PERSIST</flag>
      </flags>
      <bit_offset>65536</bit_offset>
      <format>INT_WAS_BOOL</format>
    </column>
    <column name="Uxboxflags" type="U8">
      <offset>89</offset>
      <flags>
        <flag>CLIENT_ONLY</flag>
      </flags>
    </column>
    <column name="}" type="END" />
  </table>
</parser>