<?xml version="1.0" encoding="utf-8"?>
<parser name="InfuseSlot">
  <table>
    <column name="InfuseSlot" type="IGNORE">
      <flags>
        <flag>PARSETABLE_INFO</flag>
      </flags>
    </column>
    <column name="{" type="START" />
    <column name="hDef" type="REFERENCE">
      <offset>0</offset>
      <flags>
        <flag>PERSIST</flag>
      </flags>
      <dictionary_name>InfuseSlotDef</dictionary_name>
    </column>
    <column name="Hitem" type="REFERENCE">
      <offset>8</offset>
      <flags>
        <flag>PERSIST</flag>
      </flags>
      <dictionary_name>ItemDef</dictionary_name>
    </column>
    <column name="Irefund" type="INT">
      <offset>16</offset>
      <flags>
        <flag>PERSIST</flag>
      </flags>
    </column>
    <column name="Iindex" type="INT">
      <offset>20</offset>
      <flags>
        <flag>KEY</flag>
        <flag>PERSIST</flag>
      </flags>
    </column>
    <column name="Irank" type="U8">
      <offset>24</offset>
      <flags>
        <flag>PERSIST</flag>
      </flags>
    </column>
    <column name="}" type="END" />
  </table>
</parser>