<?xml version="1.0" encoding="utf-8"?>
<parser name="MapDetectedEntry">
  <table>
    <column name="MapDetectedEntry" type="IGNORE">
      <flags>
        <flag>PARSETABLE_INFO</flag>
      </flags>
    </column>
    <column name="{" type="START" />
    <column name="Targettype" type="INT">
      <offset>0</offset>
      <static_define_list external="TargetType" />
    </column>
    <column name="Powermodes" type="INTARRAY">
      <offset>8</offset>
    </column>
    <column name="Characterclass" type="STRING">
      <offset>16</offset>
      <flags>
        <flag>POOL_STRING</flag>
      </flags>
    </column>
    <column name="V3pos" type="F32FIXEDARRAY">
      <offset>24</offset>
      <num_elements>3</num_elements>
      <format_raw>14</format_raw>
    </column>
    <column name="Rotation" type="F32">
      <offset>36</offset>
    </column>
    <column name="ContainerID" type="INT">
      <offset>40</offset>
    </column>
    <column name="Type" type="INT">
      <offset>44</offset>
      <static_define_list external="GlobalType" />
    </column>
    <column name="}" type="END" />
  </table>
</parser>