<?xml version="1.0" encoding="utf-8"?>
<parser name="SharedBankNumeric">
  <table>
    <column name="SharedBankNumeric" type="IGNORE">
      <flags>
        <flag>PARSETABLE_INFO</flag>
      </flags>
    </column>
    <column name="{" type="START" />
    <column name="Numeric" type="STRING">
      <offset>0</offset>
      <flags>
        <flag>POOL_STRING</flag>
        <flag>STRUCTPARAM</flag>
        <flag>GLOBAL_NAME</flag>
        <flag>KEY</flag>
      </flags>
      <dictionary_name>ItemDef</dictionary_name>
    </column>
    <column name="Maximumvalue" type="INT">
      <offset>8</offset>
      <default>2147483647</default>
    </column>
    <column name="File" type="CURRENTFILE">
      <offset>16</offset>
      <flags>
        <flag>POOL_STRING</flag>
      </flags>
    </column>
    <column name="}" type="END" />
  </table>
</parser>