<?xml version="1.0" encoding="utf-8"?>
<parser name="SkyTimeFog">
  <table>
    <column name="SkyTimeFog" type="IGNORE">
      <flags>
        <flag>PARSETABLE_INFO</flag>
      </flags>
    </column>
    <column name="Time" type="F32">
      <offset>0</offset>
    </column>
    <column name="Fogcolorhsv" type="F32FIXEDARRAY">
      <offset>4</offset>
      <num_elements>3</num_elements>
      <format>HSV</format>
    </column>
    <column name="Highfogcolorhsv" type="F32FIXEDARRAY">
      <offset>16</offset>
      <num_elements>3</num_elements>
      <format>HSV</format>
    </column>
    <column name="Clipfogcolorhsv" type="F32FIXEDARRAY">
      <offset>28</offset>
      <num_elements>3</num_elements>
      <format>HSV</format>
    </column>
    <column name="Clipbackgroundcolorhsv" type="F32FIXEDARRAY">
      <offset>40</offset>
      <num_elements>3</num_elements>
      <format>HSV</format>
    </column>
    <column name="Clipfogdistanceadjust" type="F32">
      <offset>52</offset>
    </column>
    <column name="Fogdist" type="F32FIXEDARRAY">
      <offset>56</offset>
      <num_elements>2</num_elements>
      <format_raw>14</format_raw>
    </column>
    <column name="Highfogdist" type="F32FIXEDARRAY">
      <offset>64</offset>
      <num_elements>2</num_elements>
      <format_raw>14</format_raw>
    </column>
    <column name="Fogmax" type="F32">
      <offset>72</offset>
    </column>
    <column name="Highfogmax" type="F32">
      <offset>76</offset>
    </column>
    <column name="Fogheight" type="F32FIXEDARRAY">
      <offset>80</offset>
      <num_elements>2</num_elements>
      <format_raw>14</format_raw>
    </column>
    <column name="Fogdensity" type="F32FIXEDARRAY">
      <offset>88</offset>
      <num_elements>2</num_elements>
      <format_raw>14</format_raw>
    </column>
    <column name="Volumefogpos" type="F32FIXEDARRAY">
      <offset>96</offset>
      <num_elements>3</num_elements>
      <format_raw>14</format_raw>
    </column>
    <column name="Volumefogscale" type="F32FIXEDARRAY">
      <offset>108</offset>
      <num_elements>3</num_elements>
      <format_raw>14</format_raw>
    </column>
    <column name="Bfparamsspecified" type="INTFIXEDARRAY">
      <offset>120</offset>
      <flags>
        <flag>USEDFIELD</flag>
        <flag>USEROPTIONBIT_1</flag>
      </flags>
      <num_elements>1</num_elements>
    </column>
    <column name="Endskyfog" type="END" />
  </table>
</parser>